kdo_test_text_writer/__init__.py
kdo_test_text_writer/server.py
kdo_test_text_writer-0.1.0.dist-info/METADATA
kdo_test_text_writer-0.1.0.dist-info/WHEEL
kdo_test_text_writer-0.1.0.dist-info/entry_points.txt
kdo_test_text_writer-0.1.0.dist-info/RECORD
